{
    data:
    {
        movies:
            [{
                "nm": "北京",
                "dir": "b",
                "rt":"2018-6-6 16:00:00",
                "img":""
            },
            {
                "name": "北京",
                "dir": "a",
                "rt":"2018-6-6 16:00:00",
                "img":""
            },
            {
                "name": "北京",
                "dir": "c",
                "rt":"2018-6-6 16:00:00",
                "img":""
            },
            {
                "name": "北京",
                "dir": "d",
                "rt":"2018-6-6 16:00:00",
                "img":""
            },
            {
                "name": "北京",
                "dir": "e",
                "rt":"2018-6-6 16:00:00",
                "img":""
            },
            {
                "name": "北京",
                "dir": "f",
                "rt":"2018-6-6 16:00:00",
                "img":""
            },
            {
                "name": "北京",
                "dir": "g",
                "rt":"2018-6-6 16:00:00",
                "img":""
            },
            {
                "name": "北京",
                "dir": "g",
                "rt":"2018-6-6 16:00:00",
                "img":""
            }]
    }
}
